{
  "regions": {
    "us": {
      "gw": 441.7,
      "delta_pct": 0.7,
      "series": [
        {
          "time": "2026-04-03T04",
          "value": 451.6
        },
        {
          "time": "2026-04-03T05",
          "value": 433.5
        },
        {
          "time": "2026-04-03T06",
          "value": 413.3
        },
        {
          "time": "2026-04-03T07",
          "value": 398.4
        },
        {
          "time": "2026-04-03T08",
          "value": 390.2
        },
        {
          "time": "2026-04-03T09",
          "value": 386.4
        },
        {
          "time": "2026-04-03T10",
          "value": 388.6
        },
        {
          "time": "2026-04-03T11",
          "value": 400.7
        },
        {
          "time": "2026-04-03T12",
          "value": 414.3
        },
        {
          "time": "2026-04-03T13",
          "value": 427.9
        },
        {
          "time": "2026-04-03T14",
          "value": 440.8
        },
        {
          "time": "2026-04-03T15",
          "value": 452.1
        },
        {
          "time": "2026-04-03T16",
          "value": 458.2
        },
        {
          "time": "2026-04-03T17",
          "value": 466.2
        },
        {
          "time": "2026-04-03T18",
          "value": 467.1
        },
        {
          "time": "2026-04-03T19",
          "value": 470.8
        },
        {
          "time": "2026-04-03T20",
          "value": 474.1
        },
        {
          "time": "2026-04-03T21",
          "value": 479.2
        },
        {
          "time": "2026-04-03T22",
          "value": 485.3
        },
        {
          "time": "2026-04-03T23",
          "value": 483.8
        },
        {
          "time": "2026-04-04T00",
          "value": 480.0
        },
        {
          "time": "2026-04-04T01",
          "value": 478.5
        },
        {
          "time": "2026-04-04T02",
          "value": 471.9
        },
        {
          "time": "2026-04-04T03",
          "value": 457.8
        },
        {
          "time": "2026-04-04T04",
          "value": 438.5
        },
        {
          "time": "2026-04-04T05",
          "value": 419.7
        },
        {
          "time": "2026-04-04T06",
          "value": 404.3
        },
        {
          "time": "2026-04-04T07",
          "value": 389.5
        },
        {
          "time": "2026-04-04T08",
          "value": 379.5
        },
        {
          "time": "2026-04-04T09",
          "value": 374.4
        },
        {
          "time": "2026-04-04T10",
          "value": 374.3
        },
        {
          "time": "2026-04-04T11",
          "value": 381.7
        },
        {
          "time": "2026-04-04T12",
          "value": 384.8
        },
        {
          "time": "2026-04-04T13",
          "value": 397.3
        },
        {
          "time": "2026-04-04T14",
          "value": 411.2
        },
        {
          "time": "2026-04-04T15",
          "value": 424.4
        },
        {
          "time": "2026-04-04T16",
          "value": 435.3
        },
        {
          "time": "2026-04-04T17",
          "value": 442.6
        },
        {
          "time": "2026-04-04T18",
          "value": 446.7
        },
        {
          "time": "2026-04-04T19",
          "value": 452.8
        },
        {
          "time": "2026-04-04T20",
          "value": 454.3
        },
        {
          "time": "2026-04-04T21",
          "value": 457.5
        },
        {
          "time": "2026-04-04T22",
          "value": 461.8
        },
        {
          "time": "2026-04-04T23",
          "value": 461.4
        },
        {
          "time": "2026-04-05T00",
          "value": 459.9
        },
        {
          "time": "2026-04-05T01",
          "value": 460.9
        },
        {
          "time": "2026-04-05T02",
          "value": 456.4
        },
        {
          "time": "2026-04-05T03",
          "value": 441.7
        }
      ],
      "updated": "2026-04-05T03"
    },
    "eu": {
      "gw": 551.0,
      "delta_pct": null,
      "series": [
        {
          "time": "2026-04-04T16:30",
          "value": 601.0
        },
        {
          "time": "2026-04-04T16:45",
          "value": 612.0
        },
        {
          "time": "2026-04-04T17:00",
          "value": 624.0
        },
        {
          "time": "2026-04-04T17:15",
          "value": 632.0
        },
        {
          "time": "2026-04-04T17:30",
          "value": 634.0
        },
        {
          "time": "2026-04-04T17:45",
          "value": 635.0
        },
        {
          "time": "2026-04-04T18:00",
          "value": 633.0
        },
        {
          "time": "2026-04-04T18:15",
          "value": 640.0
        },
        {
          "time": "2026-04-04T18:30",
          "value": 642.0
        },
        {
          "time": "2026-04-04T18:45",
          "value": 646.0
        },
        {
          "time": "2026-04-04T19:00",
          "value": 645.0
        },
        {
          "time": "2026-04-04T19:15",
          "value": 642.0
        },
        {
          "time": "2026-04-04T19:30",
          "value": 636.0
        },
        {
          "time": "2026-04-04T19:45",
          "value": 631.0
        },
        {
          "time": "2026-04-04T20:00",
          "value": 630.0
        },
        {
          "time": "2026-04-04T20:15",
          "value": 639.0
        },
        {
          "time": "2026-04-04T20:30",
          "value": 641.0
        },
        {
          "time": "2026-04-04T20:45",
          "value": 654.0
        },
        {
          "time": "2026-04-04T21:00",
          "value": 653.0
        },
        {
          "time": "2026-04-04T21:15",
          "value": 650.0
        },
        {
          "time": "2026-04-04T21:30",
          "value": 648.0
        },
        {
          "time": "2026-04-04T21:45",
          "value": 654.0
        },
        {
          "time": "2026-04-04T22:00",
          "value": 651.0
        },
        {
          "time": "2026-04-04T22:15",
          "value": 649.0
        },
        {
          "time": "2026-04-04T22:30",
          "value": 635.0
        },
        {
          "time": "2026-04-04T22:45",
          "value": 620.0
        },
        {
          "time": "2026-04-04T23:00",
          "value": 619.0
        },
        {
          "time": "2026-04-04T23:15",
          "value": 616.0
        },
        {
          "time": "2026-04-04T23:30",
          "value": 610.0
        },
        {
          "time": "2026-04-04T23:45",
          "value": 607.0
        },
        {
          "time": "2026-04-05T00:00",
          "value": 597.0
        },
        {
          "time": "2026-04-05T00:15",
          "value": 593.0
        },
        {
          "time": "2026-04-05T00:30",
          "value": 583.0
        },
        {
          "time": "2026-04-05T00:45",
          "value": 577.0
        },
        {
          "time": "2026-04-05T01:00",
          "value": 567.0
        },
        {
          "time": "2026-04-05T01:15",
          "value": 558.0
        },
        {
          "time": "2026-04-05T01:30",
          "value": 552.0
        },
        {
          "time": "2026-04-05T01:45",
          "value": 546.0
        },
        {
          "time": "2026-04-05T02:00",
          "value": 542.0
        },
        {
          "time": "2026-04-05T02:15",
          "value": 537.0
        },
        {
          "time": "2026-04-05T02:30",
          "value": 536.0
        },
        {
          "time": "2026-04-05T02:45",
          "value": 533.0
        },
        {
          "time": "2026-04-05T03:00",
          "value": 531.0
        },
        {
          "time": "2026-04-05T03:15",
          "value": 540.0
        },
        {
          "time": "2026-04-05T03:30",
          "value": 537.0
        },
        {
          "time": "2026-04-05T03:45",
          "value": 538.0
        },
        {
          "time": "2026-04-05T04:00",
          "value": 545.0
        },
        {
          "time": "2026-04-05T04:15",
          "value": 551.0
        }
      ],
      "note": "Estimated from France\u00d714",
      "updated": "2026-04-05T04:15:00+00:00"
    },
    "cn": {
      "gw": 1073,
      "twh_year": 9400,
      "note": "IEA 2023 annual avg",
      "updated": "2023"
    }
  },
  "updated": "2026-04-05T04:38:30.701781Z"
}